smh_playwright_crawl/__init__.py
smh_playwright_crawl/cli.py
smh_playwright_crawl/crawler.py
smh_playwright_crawl/utils.py
smh_playwright_crawl/config/__init__.py
smh_playwright_crawl/config/playwright_config.py
smh_playwright_crawl-0.1.10.dist-info/licenses/LICENSE
smh_playwright_crawl-0.1.10.dist-info/METADATA
smh_playwright_crawl-0.1.10.dist-info/WHEEL
smh_playwright_crawl-0.1.10.dist-info/entry_points.txt
smh_playwright_crawl-0.1.10.dist-info/top_level.txt
smh_playwright_crawl-0.1.10.dist-info/RECORD
