Metadata-Version: 2.4
Name: smh-playwright-crawl
Version: 0.1.10
Summary: An async, Playwright-powered web crawler for crawling and scraping web pages with enhanced dedup and filtering.
Author-email: S MUNI HARISH <samamuniharish@gmail.com>
License:                                  Apache License
Keywords: fire-crawl,power-crawl,playwright,web-crawler,web-scraper,async-crawler,async-scraper
Classifier: Programming Language :: Python :: 3.11
Classifier: License :: OSI Approved :: MIT License
Classifier: Operating System :: OS Independent
Requires-Python: >=3.11
License-File: LICENSE
Requires-Dist: playwright>=1.55.0
Requires-Dist: beautifulsoup4>=4.14.2
Requires-Dist: tldextract>=5.3.0
Dynamic: license-file
